gitodo/__init__.py
gitodo/main.py
gitodo-0.1.0.dist-info/METADATA
gitodo-0.1.0.dist-info/WHEEL
gitodo-0.1.0.dist-info/entry_points.txt
gitodo-0.1.0.dist-info/top_level.txt
gitodo-0.1.0.dist-info/RECORD
