Metadata-Version: 2.4
Name: gitodo
Version: 0.1.0
Summary: A simple A2A client library
Author-email: whillhill <ooooofish@126.com>
Maintainer-email: whillhill <ooooofish@126.com>
License: MIT
Project-URL: Homepage, https://github.com/whillhill/gitodo
Project-URL: Repository, https://github.com/whillhill/gitodo
Project-URL: Issues, https://github.com/whillhill/gitodo/issues
Keywords: client,a2a,api
Classifier: Development Status :: 3 - Alpha
Classifier: Intended Audience :: Developers
Classifier: License :: OSI Approved :: MIT License
Classifier: Programming Language :: Python :: 3
Classifier: Programming Language :: Python :: 3.8
Classifier: Programming Language :: Python :: 3.9
Classifier: Programming Language :: Python :: 3.10
Classifier: Programming Language :: Python :: 3.11
Classifier: Programming Language :: Python :: 3.12
Requires-Python: >=3.8
Provides-Extra: dev
Requires-Dist: pytest>=7.0; extra == "dev"
Requires-Dist: pytest-cov>=4.0; extra == "dev"
Requires-Dist: black>=22.0; extra == "dev"
Requires-Dist: flake8>=5.0; extra == "dev"
Requires-Dist: mypy>=1.0; extra == "dev"
